secp256k2/Loader.py
secp256k2/__init__.py
secp256k2/_secp256k2.dll
secp256k2/_secp256k2.so
secp256k2/constants.py
secp256k2/lib.py
secp256k2/utils.py
secp256k2-1.4.6.data/data/_secp256k2.so
secp256k2-1.4.6.dist-info/LICENSE
secp256k2-1.4.6.dist-info/METADATA
secp256k2-1.4.6.dist-info/WHEEL
secp256k2-1.4.6.dist-info/top_level.txt
secp256k2-1.4.6.dist-info/zip-safe
secp256k2-1.4.6.dist-info/RECORD
